avinashtare_hello/__init__.py
avinashtare_hello/main.py
avinashtare_hello-1.2.0.dist-info/LICENCE
avinashtare_hello-1.2.0.dist-info/METADATA
avinashtare_hello-1.2.0.dist-info/WHEEL
avinashtare_hello-1.2.0.dist-info/entry_points.txt
avinashtare_hello-1.2.0.dist-info/top_level.txt
avinashtare_hello-1.2.0.dist-info/RECORD
